kitsune/__init__.py
kitsune/constants.py
kitsune/doujin.py
kitsune/http.py
kitsune/query.py
kitsune/routes.py
kitsune/wrapper.py
kitsune_nh-0.0.7.dist-info/LICENSE.txt
kitsune_nh-0.0.7.dist-info/METADATA
kitsune_nh-0.0.7.dist-info/WHEEL
kitsune_nh-0.0.7.dist-info/top_level.txt
kitsune_nh-0.0.7.dist-info/RECORD
