Metadata-Version: 2.1
Name: kitsune-nh
Version: 0.0.7
Summary: nhentai.net API wrapper for doujins
Home-page: UNKNOWN
Author: https://github.com/Acertig
Author-email: <acertig04@gmail.com>
License: UNKNOWN
Keywords: python,wrapper,scraper,nhentai,anime,manga
Platform: UNKNOWN
Classifier: Development Status :: 5 - Production/Stable
Classifier: Intended Audience :: Developers
Classifier: Programming Language :: Python :: 3
Classifier: Operating System :: Unix
Classifier: Operating System :: Microsoft :: Windows
Requires-Dist: Pillow
Requires-Dist: aiohttp
